tokenization_local_long_doc_python.py
tokenization_local_python.py
tokenization_s3_long_doc_python.py
tokenization_transform.py
tokenization_transform_python.py
tokenization_utils.py
dpk_tokenization_transform_python-0.2.0.dist-info/METADATA
dpk_tokenization_transform_python-0.2.0.dist-info/WHEEL
dpk_tokenization_transform_python-0.2.0.dist-info/top_level.txt
dpk_tokenization_transform_python-0.2.0.dist-info/RECORD
