Metadata-Version: 2.1
Name: dpk_tokenization_transform_python
Version: 0.2.0
Summary: Tokenization Transform for Python
Author-email: Xuan-Hong Dang <xuan-hong.dang@ibm.com>
License: Apache-2.0
Keywords: tokenizer,data,data preprocessing,data preparation,llm,generative,ai,fine-tuning,llmapps
Requires-Python: >=3.10
Requires-Dist: data-prep-toolkit ==0.2.0
Requires-Dist: transformers ==4.38.0
Provides-Extra: dev
Requires-Dist: twine ; extra == 'dev'
Requires-Dist: pytest >=7.3.2 ; extra == 'dev'
Requires-Dist: pytest-dotenv >=0.5.2 ; extra == 'dev'
Requires-Dist: pytest-env >=1.0.0 ; extra == 'dev'
Requires-Dist: pre-commit >=3.3.2 ; extra == 'dev'
Requires-Dist: pytest-cov >=4.1.0 ; extra == 'dev'
Requires-Dist: pytest-mock >=3.10.0 ; extra == 'dev'
Requires-Dist: moto ==5.0.5 ; extra == 'dev'
Requires-Dist: markupsafe ==2.0.1 ; extra == 'dev'
